Atlas.cp310-win_amd64.pyd
atlas_finance-2.0.4.dist-info/METADATA
atlas_finance-2.0.4.dist-info/WHEEL
atlas_finance-2.0.4.dist-info/top_level.txt
atlas_finance-2.0.4.dist-info/RECORD
