Metadata-Version: 2.1
Name: atlas-finance
Version: 2.0.4
Summary: Pricing library for Python
Home-page: UNKNOWN
Author: Jose Melo
Author-email: jmelo@live.cl
License: UNKNOWN
Platform: UNKNOWN
Requires-Python: >=3.7
